fw_nodes_core/__init__.py
fw_nodes_core/nodes/__init__.py
fw_nodes_core/nodes/call_flow.py
fw_nodes_core/nodes/comment.py
fw_nodes_core/nodes/condition.py
fw_nodes_core/nodes/debug.py
fw_nodes_core/nodes/delay.py
fw_nodes_core/nodes/for_each.py
fw_nodes_core/nodes/generate_jsonl.py
fw_nodes_core/nodes/group.py
fw_nodes_core/nodes/html_parse.py
fw_nodes_core/nodes/http_request.py
fw_nodes_core/nodes/multi_output_test.py
fw_nodes_core/nodes/return_node.py
fw_nodes_core/nodes/s3_upload.py
fw_nodes_core/nodes/schedule_trigger.py
fw_nodes_core/nodes/set_values.py
fw_nodes_core/nodes/strip.py
fw_nodes_core/nodes/trigger.py
fw_nodes_core/nodes/webhook.py
fw_nodes_core/nodes/webhook_response.py
fw_nodes_core-0.0.1a1.dist-info/METADATA
fw_nodes_core-0.0.1a1.dist-info/WHEEL
fw_nodes_core-0.0.1a1.dist-info/entry_points.txt
fw_nodes_core-0.0.1a1.dist-info/licenses/LICENSE
fw_nodes_core-0.0.1a1.dist-info/RECORD
